<m:math_1 display='inline'><m:mrow><m:mover accent='true'><m:mi>x</m:mi><m:mo stretchy='true'>&#x00AF;</m:mo></m:mover><m:mo>=</m:mo><m:mn>58.2</m:mn><m:mtext>&#x2009;</m:mtext><m:mtext>cm</m:mtext></m:mrow></m:math_1>
<m:math_2 display='inline'><m:mrow><m:msub><m:mstyle displaystyle='true'><m:mi>s</m:mi></m:mstyle><m:mi>x</m:mi></m:msub><m:mo>=</m:mo><m:mn>13.20</m:mn><m:mtext>&#x2009;</m:mtext><m:mtext>&#x200B;</m:mtext><m:mtext>cm</m:mtext></m:mrow></m:math_2>
<m:math_3 display='inline'><m:mrow><m:mover accent='true'><m:mi>y</m:mi><m:mo stretchy='true'>&#x00AF;</m:mo></m:mover><m:mo>=</m:mo><m:mn>66.0</m:mn><m:mtext>&#x2009;</m:mtext><m:mtext>cm</m:mtext></m:mrow></m:math_3>
<m:math_4 display='inline'><m:mrow><m:msub><m:mstyle displaystyle='true'><m:mi>s</m:mi></m:mstyle><m:mi>y</m:mi></m:msub><m:mo>=</m:mo><m:mn>15.89</m:mn><m:mtext>&#x2009;</m:mtext><m:mtext>&#x200B;</m:mtext><m:mtext>cm</m:mtext></m:mrow></m:math_4>
<m:math_5 display='inline'><m:mrow><m:mrow><m:mo>(</m:mo><m:mrow><m:mi>x</m:mi><m:mo>&#x2212;</m:mo><m:mover accent='true'><m:mi>x</m:mi><m:mo stretchy='true'>&#x00AF;</m:mo></m:mover></m:mrow><m:mo>)</m:mo></m:mrow><m:mo>/</m:mo><m:msub><m:mstyle displaystyle='true'><m:mi>s</m:mi></m:mstyle><m:mi>x</m:mi></m:msub></m:mrow></m:math_5>
<m:math_6 display='inline'><m:mrow><m:mrow><m:mo>(</m:mo><m:mrow><m:mi>y</m:mi><m:mo>&#x2212;</m:mo><m:mover accent='true'><m:mi>y</m:mi><m:mo stretchy='true'>&#x00AF;</m:mo></m:mover></m:mrow><m:mo>)</m:mo></m:mrow><m:mo>/</m:mo><m:msub><m:mstyle displaystyle='true'><m:mi>s</m:mi></m:mstyle><m:mi>y</m:mi></m:msub></m:mrow></m:math_6>
<m:math_7 display='inline'><m:mrow><m:mrow><m:mo>(</m:mo><m:mrow><m:mn>38</m:mn><m:mo>&#x2212;</m:mo><m:mn>58.2</m:mn></m:mrow><m:mo>)</m:mo></m:mrow><m:mo>/</m:mo><m:mn>13.20</m:mn><m:mo>=</m:mo><m:mo>&#x2212;</m:mo><m:mn>1.530</m:mn></m:mrow></m:math_7>
<m:math_8 display='inline'><m:mrow><m:mrow><m:mo>(</m:mo><m:mrow><m:mn>41</m:mn><m:mo>&#x2212;</m:mo><m:mn>66.0</m:mn></m:mrow><m:mo>)</m:mo></m:mrow><m:mo>/</m:mo><m:mn>15.89</m:mn><m:mo>=</m:mo><m:mo>&#x2212;</m:mo><m:mn>1.573</m:mn></m:mrow></m:math_8>
<m:math_9 display='inline'><m:mrow><m:mrow><m:mo>(</m:mo><m:mrow><m:mn>56</m:mn><m:mo>&#x2212;</m:mo><m:mn>58.2</m:mn></m:mrow><m:mo>)</m:mo></m:mrow><m:mo>/</m:mo><m:mn>13.20</m:mn><m:mo>=</m:mo><m:mo>&#x2212;</m:mo><m:mn>0.167</m:mn></m:mrow></m:math_9>
<m:math_10 display='inline'><m:mrow><m:mrow><m:mo>(</m:mo><m:mrow><m:mn>63</m:mn><m:mo>&#x2212;</m:mo><m:mn>66.0</m:mn></m:mrow><m:mo>)</m:mo></m:mrow><m:mo>/</m:mo><m:mn>15.89</m:mn><m:mo>=</m:mo><m:mo>&#x2212;</m:mo><m:mn>0.189</m:mn></m:mrow></m:math_10>
<m:math_11 display='inline'><m:mrow><m:mrow><m:mo>(</m:mo><m:mrow><m:mn>59</m:mn><m:mo>&#x2212;</m:mo><m:mn>58.2</m:mn></m:mrow><m:mo>)</m:mo></m:mrow><m:mo>/</m:mo><m:mn>13.20</m:mn><m:mo>=</m:mo><m:mtext>&#x00A0;</m:mtext><m:mn>0.061</m:mn></m:mrow></m:math_11>
<m:math_12 display='inline'><m:mrow><m:mrow><m:mo>(</m:mo><m:mrow><m:mn>70</m:mn><m:mo>&#x2212;</m:mo><m:mn>66.0</m:mn></m:mrow><m:mo>)</m:mo></m:mrow><m:mo>/</m:mo><m:mn>15.89</m:mn><m:mo>=</m:mo><m:mtext>&#x00A0;</m:mtext><m:mn>0.252</m:mn></m:mrow></m:math_12>
<m:math_13 display='inline'><m:mrow><m:mrow><m:mo>(</m:mo><m:mrow><m:mn>64</m:mn><m:mo>&#x2212;</m:mo><m:mn>58.2</m:mn></m:mrow><m:mo>)</m:mo></m:mrow><m:mo>/</m:mo><m:mn>13.20</m:mn><m:mo>=</m:mo><m:mtext>&#x00A0;</m:mtext><m:mn>0.439</m:mn></m:mrow></m:math_13>
<m:math_14 display='inline'><m:mrow><m:mrow><m:mo>(</m:mo><m:mrow><m:mn>72</m:mn><m:mo>&#x2212;</m:mo><m:mn>66.0</m:mn></m:mrow><m:mo>)</m:mo></m:mrow><m:mo>/</m:mo><m:mn>15.89</m:mn><m:mo>=</m:mo><m:mtext>&#x00A0;</m:mtext><m:mn>0.378</m:mn></m:mrow></m:math_14>
<m:math_15 display='inline'><m:mrow><m:mrow><m:mo>(</m:mo><m:mrow><m:mn>74</m:mn><m:mo>&#x2212;</m:mo><m:mn>58.2</m:mn></m:mrow><m:mo>)</m:mo></m:mrow><m:mo>/</m:mo><m:mn>13.20</m:mn><m:mo>=</m:mo><m:mtext>&#x00A0;</m:mtext><m:mn>1.197</m:mn></m:mrow></m:math_15>
<m:math_16 display='inline'><m:mrow><m:mrow><m:mo>(</m:mo><m:mrow><m:mn>84</m:mn><m:mo>&#x2212;</m:mo><m:mn>66.0</m:mn></m:mrow><m:mo>)</m:mo></m:mrow><m:mo>/</m:mo><m:mn>15.89</m:mn><m:mo>=</m:mo><m:mtext>&#x00A0;</m:mtext><m:mn>1.133</m:mn></m:mrow></m:math_16>
<m:math_17 display='block'><m:mtable columnalign='left'><m:mtr columnalign="left"><m:mtd columnalign='right'><m:mstyle displaystyle='true'><m:mi>r</m:mi></m:mstyle></m:mtd><m:mtd columnalign='left'><m:mstyle displaystyle='true'><m:mo>=</m:mo></m:mstyle></m:mtd><m:mtd columnalign='left'><m:mstyle displaystyle='true'><m:mfrac><m:mn>1</m:mn><m:mn>4</m:mn></m:mfrac><m:mrow><m:mo>[</m:mo><m:mrow><m:mrow><m:mo>(</m:mo><m:mrow><m:mo>&#x2212;</m:mo><m:mn>1.530</m:mn></m:mrow><m:mo>)</m:mo></m:mrow><m:mrow><m:mo>(</m:mo><m:mrow><m:mo>&#x2212;</m:mo><m:mn>1.573</m:mn></m:mrow><m:mo>)</m:mo></m:mrow><m:mo>+</m:mo></m:mrow></m:mrow><m:mrow><m:mo>(</m:mo><m:mrow><m:mo>&#x2212;</m:mo><m:mn>0.167</m:mn></m:mrow><m:mo>)</m:mo></m:mrow><m:mrow><m:mo>(</m:mo><m:mrow><m:mo>&#x2212;</m:mo><m:mn>0.189</m:mn></m:mrow><m:mo>)</m:mo></m:mrow><m:mo>+</m:mo><m:mrow><m:mo>(</m:mo><m:mrow><m:mn>0.061</m:mn></m:mrow><m:mo>)</m:mo></m:mrow><m:mrow><m:mo>(</m:mo><m:mrow><m:mn>0.252</m:mn></m:mrow><m:mo>)</m:mo></m:mrow></m:mstyle></m:mtd></m:mtr><m:mtr columnalign="left"><m:mtd columnalign='right'/><m:mtd columnalign='left'/><m:mtd columnalign='left'><m:mstyle displaystyle='true'><m:mrow><m:mrow><m:mtext>&#x2009;</m:mtext><m:mtext>&#x2009;</m:mtext><m:mtext>&#x2009;</m:mtext><m:mtext>&#x2009;</m:mtext><m:mtext>&#x2009;</m:mtext><m:mtext>&#x2009;</m:mtext><m:mtext>&#x2009;</m:mtext><m:mtext>&#x2009;</m:mtext><m:mtext>&#x2009;</m:mtext><m:mtext>&#x2009;</m:mtext><m:mtext>&#x2009;</m:mtext><m:mtext>&#x2009;</m:mtext><m:mtext>&#x2009;</m:mtext><m:mtext>&#x2009;</m:mtext><m:mtext>&#x2009;</m:mtext><m:mtext>&#x2009;</m:mtext><m:mtext>&#x2009;</m:mtext><m:mtext>&#x2009;</m:mtext><m:mtext>&#x2009;</m:mtext><m:mtext>&#x2009;</m:mtext><m:mtext>&#x2009;</m:mtext><m:mtext>&#x2009;</m:mtext><m:mtext>&#x2009;</m:mtext><m:mtext>&#x2009;</m:mtext><m:mtext>&#x2009;</m:mtext><m:mtext>&#x2009;</m:mtext><m:mtext>&#x2009;</m:mtext><m:mtext>&#x2009;</m:mtext><m:mtext>&#x2009;</m:mtext><m:mtext>&#x2009;</m:mtext><m:mtext>&#x2009;</m:mtext><m:mtext>&#x2009;</m:mtext><m:mtext>&#x2009;</m:mtext><m:mtext>&#x2009;</m:mtext><m:mtext>&#x2009;</m:mtext><m:mtext>&#x2009;</m:mtext><m:mtext>&#x2009;</m:mtext><m:mtext>&#x2009;</m:mtext><m:mtext>&#x2009;</m:mtext><m:mtext>&#x2009;</m:mtext><m:mtext>&#x2009;</m:mtext><m:mtext>&#x2009;</m:mtext><m:mtext>&#x2009;</m:mtext><m:mtext>&#x2009;</m:mtext><m:mtext>&#x2009;</m:mtext><m:mtext>&#x2009;</m:mtext><m:mtext>&#x2009;</m:mtext><m:mtext>&#x2009;</m:mtext><m:mtext>&#x2009;</m:mtext><m:mo>+</m:mo><m:mrow><m:mo>(</m:mo><m:mrow><m:mn>0.439</m:mn></m:mrow><m:mo>)</m:mo></m:mrow><m:mrow><m:mo>(</m:mo><m:mrow><m:mn>0.378</m:mn></m:mrow><m:mo>)</m:mo></m:mrow><m:mo>+</m:mo><m:mrow><m:mo>(</m:mo><m:mrow><m:mn>1.197</m:mn></m:mrow><m:mo>)</m:mo></m:mrow><m:mrow><m:mo>(</m:mo><m:mrow><m:mn>1.133</m:mn></m:mrow><m:mo>)</m:mo></m:mrow></m:mrow><m:mo>]</m:mo></m:mrow></m:mstyle></m:mtd></m:mtr><m:mtr columnalign="left"><m:mtd columnalign='right'/><m:mtd columnalign='left'><m:mstyle displaystyle='true'><m:mo>=</m:mo></m:mstyle></m:mtd><m:mtd columnalign='left'><m:mstyle displaystyle='true'><m:mfrac><m:mn>1</m:mn><m:mn>4</m:mn></m:mfrac><m:mtext>(2</m:mtext><m:mtext>.4067&#x00A0;+&#x00A0;0</m:mtext><m:mtext>.0316&#x00A0;+&#x00A0;0</m:mtext><m:mtext>.0154&#x00A0;+&#x00A0;0</m:mtext><m:mtext>.1659&#x00A0;+&#x00A0;1</m:mtext><m:mtext>.3562)</m:mtext></m:mstyle></m:mtd></m:mtr><m:mtr columnalign="left"><m:mtd columnalign='right'/><m:mtd columnalign='left'><m:mstyle displaystyle='true'><m:mo>=</m:mo></m:mstyle></m:mtd><m:mtd columnalign='left'><m:mstyle displaystyle='true'><m:mfrac><m:mrow><m:mn>3.9758</m:mn></m:mrow><m:mn>4</m:mn></m:mfrac><m:mo>=</m:mo><m:mn>0.994</m:mn></m:mstyle></m:mtd></m:mtr></m:mtable></m:math_17>
<m:math_18 display='block'><m:mi>r</m:mi><m:mo>=</m:mo><m:mfrac><m:mn>1</m:mn><m:mrow><m:mi>n</m:mi><m:mo>&#x2212;</m:mo><m:mn>1</m:mn></m:mrow></m:mfrac><m:mstyle displaystyle='true'><m:mo>&#x2211;</m:mo><m:mrow><m:mrow><m:mo>(</m:mo><m:mrow><m:mfrac><m:mrow><m:mi>x</m:mi><m:mo>&#x2212;</m:mo><m:mover accent='true'><m:mi>x</m:mi><m:mo stretchy='true'>&#x00AF;</m:mo></m:mover></m:mrow><m:mrow><m:msub><m:mstyle displaystyle='true'><m:mi>s</m:mi></m:mstyle><m:mi>x</m:mi></m:msub></m:mrow></m:mfrac></m:mrow><m:mo>)</m:mo></m:mrow><m:mrow><m:mo>(</m:mo><m:mrow><m:mfrac><m:mrow><m:mi>y</m:mi><m:mo>&#x2212;</m:mo><m:mover accent='true'><m:mi>y</m:mi><m:mo stretchy='true'>&#x00AF;</m:mo></m:mover></m:mrow><m:mrow><m:msub><m:mstyle displaystyle='true'><m:mi>s</m:mi></m:mstyle><m:mi>y</m:mi></m:msub></m:mrow></m:mfrac></m:mrow><m:mo>)</m:mo></m:mrow></m:mrow></m:mstyle></m:math_18>
<m:math_19 display='inline'><m:mo>&#x2211;</m:mo></m:math_19>
<m:math_20 display='inline'><m:mrow><m:mover accent='true'><m:mi>x</m:mi><m:mo stretchy='true'>&#x00AF;</m:mo></m:mover></m:mrow></m:math_20>
<m:math_21 display='inline'><m:mi>r</m:mi></m:math_21>
